BitwiseExpressionSimplifier/__init__.py
BitwiseExpressionSimplifier/Bitwise/__init__.py
BitwiseExpressionSimplifier/Number/__init__.py
BitwiseExpressionSimplifier/util/__init__.py
BitwiseExpressionSimplifier-1.0.3.dist-info/LICENSE
BitwiseExpressionSimplifier-1.0.3.dist-info/METADATA
BitwiseExpressionSimplifier-1.0.3.dist-info/WHEEL
BitwiseExpressionSimplifier-1.0.3.dist-info/top_level.txt
BitwiseExpressionSimplifier-1.0.3.dist-info/RECORD
