Metadata-Version: 2.1
Name: BitwiseExpressionSimplifier
Version: 1.0.3
Summary: 位运算表达式化简器，支持各种你能想到的用法
Home-page: https://github.com/WankkoRee/BitwiseExpressionSimplifier
Author: Wankko Ree
Author-email: wkr@wkr.moe
License: GPLv3
Project-URL: Bug Tracker, https://github.com/WankkoRee/BitwiseExpressionSimplifier/issues
Platform: UNKNOWN
Classifier: Development Status :: 4 - Beta
Classifier: Programming Language :: Python :: 3 :: Only
Classifier: Programming Language :: Python :: 3.7
Classifier: Programming Language :: Python :: 3.8
Classifier: Programming Language :: Python :: 3.9
Classifier: License :: OSI Approved :: GNU General Public License v3 (GPLv3)
Classifier: Operating System :: OS Independent
Classifier: Natural Language :: Chinese (Simplified)
Classifier: Natural Language :: English
Requires-Python: >=3.7
